wavelink/__init__.py
wavelink/backoff.py
wavelink/enums.py
wavelink/exceptions.py
wavelink/filters.py
wavelink/node.py
wavelink/payloads.py
wavelink/player.py
wavelink/queue.py
wavelink/tracks.py
wavelink/websocket.py
wavelink/ext/spotify/__init__.py
wavelink/types/events.py
wavelink/types/request.py
wavelink/types/state.py
wavelink/types/track.py
WavelinkPycord-2.5.1.dist-info/LICENSE
WavelinkPycord-2.5.1.dist-info/METADATA
WavelinkPycord-2.5.1.dist-info/WHEEL
WavelinkPycord-2.5.1.dist-info/top_level.txt
WavelinkPycord-2.5.1.dist-info/RECORD
